eu/__init__.py
eu-0.0.9.dist-info/licenses/LICENSE
eu-0.0.9.dist-info/METADATA
eu-0.0.9.dist-info/WHEEL
eu-0.0.9.dist-info/top_level.txt
eu-0.0.9.dist-info/RECORD
