Metadata-Version: 2.4
Name: eu
Version: 0.0.9
Summary: It's good practice to write code that can be run as is on someone elses computer (or server).
Home-page: https://github.com/t-c-w/eu
Author: Thor Whalen
License: apache-2.0
Platform: any
License-File: LICENSE
Dynamic: license-file
